{
  "main": {
    "id": "2f7f58c346961c70",
    "type": "split",
    "children": [
      {
        "id": "8ba95cf945eaa6e1",
        "type": "tabs",
        "children": [
          {
            "id": "88457e27f5dfbb09",
            "type": "leaf",
            "state": {
              "type": "kanban",
              "state": {
                "file": "TODO.md",
                "kanbanViewState": {
                  "kanban-plugin": "board",
                  "list-collapse": [
                    false,
                    false,
                    false,
                    false,
                    false
                  ]
                }
              }
            }
          }
        ]
      }
    ],
    "direction": "vertical"
  },
  "left": {
    "id": "862ab34853c0b56f",
    "type": "split",
    "children": [
      {
        "id": "93dce4e319f0c62a",
        "type": "tabs",
        "children": [
          {
            "id": "b65d0c41c53be996",
            "type": "leaf",
            "state": {
              "type": "file-explorer",
              "state": {
                "sortOrder": "alphabetical"
              }
            }
          },
          {
            "id": "c23095051f5e0f10",
            "type": "leaf",
            "state": {
              "type": "search",
              "state": {
                "query": "tag:#tech",
                "matchingCase": false,
                "explainSearch": false,
                "collapseAll": false,
                "extraContext": false,
                "sortOrder": "alphabetical"
              }
            }
          },
          {
            "id": "6d13736ee49d550b",
            "type": "leaf",
            "state": {
              "type": "bookmarks",
              "state": {}
            }
          }
        ]
      }
    ],
    "direction": "horizontal",
    "width": 300
  },
  "right": {
    "id": "1975a3130d9313d7",
    "type": "split",
    "children": [
      {
        "id": "a680d751108ddef6",
        "type": "tabs",
        "children": [
          {
            "id": "025da022c7bbcf81",
            "type": "leaf",
            "state": {
              "type": "backlink",
              "state": {
                "file": "TODO.md",
                "collapseAll": false,
                "extraContext": false,
                "sortOrder": "alphabetical",
                "showSearch": false,
                "searchQuery": "",
                "backlinkCollapsed": false,
                "unlinkedCollapsed": true
              }
            }
          },
          {
            "id": "b53cdfb11dd946da",
            "type": "leaf",
            "state": {
              "type": "outgoing-link",
              "state": {
                "file": "TODO.md",
                "linksCollapsed": false,
                "unlinkedCollapsed": true
              }
            }
          },
          {
            "id": "0da8c2d3098542e4",
            "type": "leaf",
            "state": {
              "type": "tag",
              "state": {
                "sortOrder": "frequency",
                "useHierarchy": true
              }
            }
          },
          {
            "id": "564854e76e020575",
            "type": "leaf",
            "state": {
              "type": "outline",
              "state": {
                "file": "TODO.md"
              }
            }
          }
        ]
      }
    ],
    "direction": "horizontal",
    "width": 300,
    "collapsed": true
  },
  "left-ribbon": {
    "hiddenItems": {
      "switcher:Open quick switcher": false,
      "graph:Open graph view": false,
      "canvas:Create new canvas": false,
      "daily-notes:Open today's daily note": false,
      "templates:Insert template": false,
      "command-palette:Open command palette": false,
      "obsidian-kanban:Create new board": false
    }
  },
  "active": "88457e27f5dfbb09",
  "lastOpenFiles": [
    "app/PokeScout/pokescout/developer/build/intermediates/hilt/component_classes/debug/com/example/developer/DaggerDeveloperApp_HiltComponents_SingletonC$ActivityRetainedCImpl.class",
    "app/PokeScout/pokescout/developer/build/intermediates/hilt/component_classes/debug/com/example/developer/DaggerDeveloperApp_HiltComponents_SingletonC$ActivityRetainedCImpl$SwitchingProvider.class",
    "app/PokeScout/pokescout/developer/build/intermediates/hilt/component_classes/debug/com/example/developer/DaggerDeveloperApp_HiltComponents_SingletonC$ViewModelCImpl.class",
    "app/PokeScout/pokescout/developer/build/intermediates/hilt/component_classes/debug/com/example/developer/DaggerDeveloperApp_HiltComponents_SingletonC$ActivityCBuilder.class",
    "app/PokeScout/pokescout/developer/build/intermediates/hilt/component_classes/debug/com/example/developer/Hilt_DeveloperApp$1.class",
    "app/PokeScout/pokescout/developer/build/intermediates/hilt/component_classes/debug/com/example/developer/DeveloperApp_HiltComponents$ViewC$Builder.class",
    "app/PokeScout/pokescout/developer/build/intermediates/hilt/component_classes/debug/com/example/developer/DeveloperApp_HiltComponents$ViewWithFragmentCBuilderModule.class",
    "app/PokeScout/pokescout/developer/build/tmp/hiltJavaCompileDebug/compileTransaction/backup-dir/DeveloperApp_GeneratedInjector.class1",
    "app/PokeScout/pokescout/developer/build/generated/hilt/component_sources/debug/com/example/developer/DaggerDeveloperApp_HiltComponents_SingletonC.java",
    "app/PokeScout/pokescout/developer/build/generated/hilt/component_sources/debug/com/example/developer/DeveloperApp_HiltComponents.java",
    "app/PokeScout/pokescout/developer/build/intermediates/javac/debug/classes/com/example/developer/presentation/viewmodel/DeveloperViewModel_HiltModules_KeyModule_ProvideFactory.class",
    "README.md",
    "TODO.md",
    "app/PokeScout/pokescout/developer/build/intermediates/packaged_res/debug/mipmap-xxxhdpi-v4/ic_launcher_round.webp",
    "app/PokeScout/pokescout/developer/build/intermediates/packaged_res/debug/mipmap-xxxhdpi-v4/ic_launcher.webp",
    "app/PokeScout/pokescout/developer/build/intermediates/packaged_res/debug/mipmap-xhdpi-v4/ic_launcher_round.webp",
    "app/PokeScout/pokescout/developer/build/intermediates/packaged_res/debug/mipmap-xxhdpi-v4/ic_launcher_round.webp",
    "app/PokeScout/pokescout/developer/build/intermediates/packaged_res/debug/mipmap-xhdpi-v4/ic_launcher.webp",
    "app/PokeScout/pokescout/developer/build/intermediates/packaged_res/debug/mipmap-xxhdpi-v4/ic_launcher.webp",
    "app/PokeScout/pokescout/developer/build/intermediates/packaged_res/debug/mipmap-mdpi-v4/ic_launcher_round.webp",
    "app/PokeScout/pokescout/developer/build/intermediates/packaged_res/debug/mipmap-mdpi-v4/ic_launcher.webp",
    "app/PokeScout/pokescout/developer/build/intermediates/packaged_res/debug/mipmap-hdpi-v4/ic_launcher_round.webp",
    "app/PokeScout/pokescout/developer/build/intermediates/packaged_res/debug/mipmap-hdpi-v4/ic_launcher.webp",
    "MANIFEST.md"
  ]
}